{
  "id": "demo",
  "name": {
    "en": "Al Qusais Police Station",
    "ar": "┘Е╪▒┘Г╪▓ ╪┤╪▒╪╖╪й ╪з┘Д┘В╪╡┘К╪╡",
    "hi": "рдЕрд▓ рдХреБрд╕реИрд╕ рдкреБрд▓рд┐рд╕ рд╕реНрдЯреЗрд╢рди"
  },
  "address": {
    "en": "Al Qusais, Dubai, UAE",
    "ar": "╪з┘Д┘В╪╡┘К╪╡╪М ╪п╪и┘К╪М ╪з┘Д╪е┘Е╪з╪▒╪з╪к",
    "hi": "рдЕрд▓ рдХреБрд╕реИрд╕, рджреБрдмрдИ, рдпреВрдПрдИ"
  },
  "defaultStartNode": "entrance",
  "floors": [
    {
      "id": "ground",
      "name": {
        "en": "Ground Floor",
        "ar": "╪з┘Д╪╖╪з╪и┘В ╪з┘Д╪г╪▒╪╢┘К",
        "hi": "рднреВрддрд▓"
      },
      "level": 0,
      "planImage": "/floor-plan.png",
      "width": 1407,
      "height": 1135,
      "nodes": [
        {
          "id": "entrance",
          "x": 764,
          "y": 840,
          "label": {
            "en": "Entrance",
            "ar": "╪з┘Д┘Е╪п╪о┘Д",
            "hi": "рдкреНрд░рд╡реЗрд╢"
          }
        },
        {
          "id": "c_entrance",
          "x": 700,
          "y": 770,
          "label": {
            "en": "Entry Hall",
            "ar": "╪и┘З┘И ╪з┘Д╪п╪о┘И┘Д",
            "hi": "рдкреНрд░рд╡реЗрд╢ рд╣реЙрд▓"
          }
        },
        {
          "id": "reception",
          "x": 458,
          "y": 580,
          "label": {
            "en": "Reception Counter",
            "ar": "┘Е┘Г╪к╪и ╪з┘Д╪з╪│╪к┘В╪и╪з┘Д",
            "hi": "рд░рд┐рд╕реЗрдкреНрд╢рди рдХрд╛рдЙрдВрдЯрд░"
          }
        },
        {
          "id": "information",
          "x": 665,
          "y": 460,
          "label": {
            "en": "Information",
            "ar": "╪з┘Д╪з╪│╪к╪╣┘Д╪з┘Е╪з╪к",
            "hi": "рд╕реВрдЪрдирд╛"
          }
        },
        {
          "id": "c_main",
          "x": 665,
          "y": 580,
          "label": {
            "en": "Main Hall",
            "ar": "╪з┘Д╪╡╪з┘Д╪й ╪з┘Д╪▒╪ж┘К╪│┘К╪й",
            "hi": "рдореБрдЦреНрдп рд╣реЙрд▓"
          }
        },
        {
          "id": "male_toilets",
          "x": 552,
          "y": 693,
          "label": {
            "en": "Male Toilets",
            "ar": "╪п┘И╪▒╪з╪к ┘Е┘К╪з┘З ╪з┘Д╪▒╪м╪з┘Д",
            "hi": "рдкреБрд░реБрд╖ рд╢реМрдЪрд╛рд▓рдп"
          }
        },
        {
          "id": "female_toilet",
          "x": 798,
          "y": 694,
          "label": {
            "en": "Female Toilet",
            "ar": "╪п┘И╪▒╪з╪к ┘Е┘К╪з┘З ╪з┘Д┘Ж╪│╪з╪б",
            "hi": "рдорд╣рд┐рд▓рд╛ рд╢реМрдЪрд╛рд▓рдп"
          }
        },
        {
          "id": "c_left_wing",
          "x": 350,
          "y": 506,
          "label": {
            "en": "Left Wing",
            "ar": "╪з┘Д╪м┘Ж╪з╪н ╪з┘Д╪г┘К╪│╪▒",
            "hi": "рдмрд╛рдпрд╛рдБ рд╡рд┐рдВрдЧ"
          }
        },
        {
          "id": "c_right_wing",
          "x": 950,
          "y": 506,
          "label": {
            "en": "Right Wing",
            "ar": "╪з┘Д╪м┘Ж╪з╪н ╪з┘Д╪г┘К┘Е┘Ж",
            "hi": "рджрд╛рдпрд╛рдБ рд╡рд┐рдВрдЧ"
          }
        },
        {
          "id": "room_left_1",
          "x": 407,
          "y": 506,
          "label": {
            "en": "Office Room 1",
            "ar": "╪║╪▒┘Б╪й ┘Е┘Г╪к╪и ┘б",
            "hi": "рдХрд╛рд░реНрдпрд╛рд▓рдп рдХрдХреНрд╖ 1"
          }
        },
        {
          "id": "room_right_1",
          "x": 913,
          "y": 506,
          "label": {
            "en": "Office Room 2",
            "ar": "╪║╪▒┘Б╪й ┘Е┘Г╪к╪и ┘в",
            "hi": "рдХрд╛рд░реНрдпрд╛рд▓рдп рдХрдХреНрд╖ 2"
          }
        },
        {
          "id": "room_large_l",
          "x": 106,
          "y": 478,
          "label": {
            "en": "Conference Room",
            "ar": "┘В╪з╪╣╪й ╪з┘Д╪з╪м╪к┘Е╪з╪╣╪з╪к",
            "hi": "рд╕рдореНрдореЗрд▓рди рдХрдХреНрд╖"
          }
        },
        {
          "id": "room_large_r",
          "x": 1120,
          "y": 527,
          "label": {
            "en": "Investigation Room",
            "ar": "╪║╪▒┘Б╪й ╪з┘Д╪к╪н┘В┘К┘В",
            "hi": "рдЬрд╛рдВрдЪ рдХрдХреНрд╖"
          }
        },
        {
          "id": "c_north",
          "x": 665,
          "y": 300,
          "label": {
            "en": "North Corridor",
            "ar": "╪з┘Д┘Е┘Е╪▒ ╪з┘Д╪┤┘Е╪з┘Д┘К",
            "hi": "рдЙрддреНрддрд░реА рдЧрд▓рд┐рдпрд╛рд░рд╛"
          }
        },
        {
          "id": "room_nw_1",
          "x": 263,
          "y": 197,
          "label": {
            "en": "Traffic Department",
            "ar": "┘В╪│┘Е ╪з┘Д┘Е╪▒┘И╪▒",
            "hi": "рдпрд╛рддрд╛рдпрд╛рдд рд╡рд┐рднрд╛рдЧ"
          }
        },
        {
          "id": "room_ne_1",
          "x": 1072,
          "y": 197,
          "label": {
            "en": "Criminal Investigation",
            "ar": "╪з┘Д╪к╪н┘В┘К┘В╪з╪к ╪з┘Д╪м┘Ж╪з╪ж┘К╪й",
            "hi": "рдЖрдкрд░рд╛рдзрд┐рдХ рдЬрд╛рдВрдЪ"
          }
        },
        {
          "id": "room_nw_top",
          "x": 115,
          "y": 110,
          "label": {
            "en": "Commander Office",
            "ar": "┘Е┘Г╪к╪и ╪з┘Д┘В╪з╪ж╪п",
            "hi": "рдХрдорд╛рдВрдбрд░ рдХрд╛рд░реНрдпрд╛рд▓рдп"
          }
        },
        {
          "id": "room_nw_mid",
          "x": 115,
          "y": 245,
          "label": {
            "en": "Community Services",
            "ar": "╪з┘Д╪о╪п┘Е╪з╪к ╪з┘Д┘Е╪м╪к┘Е╪╣┘К╪й",
            "hi": "рд╕рд╛рдореБрджрд╛рдпрд┐рдХ рд╕реЗрд╡рд╛рдПрдВ"
          }
        },
        {
          "id": "room_ne_top",
          "x": 1223,
          "y": 91,
          "label": {
            "en": "IT Department",
            "ar": "┘В╪│┘Е ╪к┘В┘Ж┘К╪й ╪з┘Д┘Е╪╣┘Д┘И┘Е╪з╪к",
            "hi": "рдЖрдИрдЯреА рд╡рд┐рднрд╛рдЧ"
          }
        },
        {
          "id": "room_ne_mid",
          "x": 1215,
          "y": 245,
          "label": {
            "en": "Records Room",
            "ar": "╪║╪▒┘Б╪й ╪з┘Д╪│╪м┘Д╪з╪к",
            "hi": "рд░рд┐рдХреЙрд░реНрдб рдХрдХреНрд╖"
          }
        },
        {
          "id": "room_sw",
          "x": 326,
          "y": 767,
          "label": {
            "en": "Waiting Area",
            "ar": "┘Е┘Ж╪╖┘В╪й ╪з┘Д╪з┘Ж╪к╪╕╪з╪▒",
            "hi": "рдкреНрд░рддреАрдХреНрд╖рд╛ рдХреНрд╖реЗрддреНрд░"
          }
        },
        {
          "id": "room_se",
          "x": 1004,
          "y": 767,
          "label": {
            "en": "Security Room",
            "ar": "╪║╪▒┘Б╪й ╪з┘Д╪г┘Е┘Ж",
            "hi": "рд╕реБрд░рдХреНрд╖рд╛ рдХрдХреНрд╖"
          }
        },
        {
          "id": "parking",
          "x": 1145,
          "y": 1064,
          "label": {
            "en": "Parking",
            "ar": "╪з┘Д┘Е┘И╪з┘В┘Б",
            "hi": "рдкрд╛рд░реНрдХрд┐рдВрдЧ"
          }
        },
        {
          "id": "c_south_w",
          "x": 450,
          "y": 700,
          "label": {
            "en": "South West",
            "ar": "╪з┘Д╪м┘Ж┘И╪и ╪з┘Д╪║╪▒╪и┘К",
            "hi": "рджрдХреНрд╖рд┐рдг рдкрд╢реНрдЪрд┐рдо"
          }
        },
        {
          "id": "c_south_e",
          "x": 850,
          "y": 700,
          "label": {
            "en": "South East",
            "ar": "╪з┘Д╪м┘Ж┘И╪и ╪з┘Д╪┤╪▒┘В┘К",
            "hi": "рджрдХреНрд╖рд┐рдг рдкреВрд░реНрд╡реА"
          }
        }
      ],
      "edges": [
        {
          "from": "entrance",
          "to": "c_entrance",
          "weight": 7,
          "stairs": false
        },
        {
          "from": "c_entrance",
          "to": "c_main",
          "weight": 19,
          "stairs": false
        },
        {
          "from": "c_entrance",
          "to": "c_south_w",
          "weight": 25,
          "stairs": false
        },
        {
          "from": "c_entrance",
          "to": "c_south_e",
          "weight": 15,
          "stairs": false
        },
        {
          "from": "c_main",
          "to": "reception",
          "weight": 21,
          "stairs": false
        },
        {
          "from": "c_main",
          "to": "information",
          "weight": 12,
          "stairs": false
        },
        {
          "from": "c_main",
          "to": "c_left_wing",
          "weight": 32,
          "stairs": false
        },
        {
          "from": "c_main",
          "to": "c_right_wing",
          "weight": 29,
          "stairs": false
        },
        {
          "from": "c_main",
          "to": "c_north",
          "weight": 28,
          "stairs": false
        },
        {
          "from": "c_south_w",
          "to": "male_toilets",
          "weight": 10,
          "stairs": false
        },
        {
          "from": "c_south_w",
          "to": "room_sw",
          "weight": 12,
          "stairs": false
        },
        {
          "from": "c_south_e",
          "to": "female_toilet",
          "weight": 5,
          "stairs": false
        },
        {
          "from": "c_south_e",
          "to": "room_se",
          "weight": 15,
          "stairs": false
        },
        {
          "from": "c_south_e",
          "to": "parking",
          "weight": 40,
          "stairs": false
        },
        {
          "from": "c_left_wing",
          "to": "room_left_1",
          "weight": 6,
          "stairs": false
        },
        {
          "from": "c_left_wing",
          "to": "room_large_l",
          "weight": 25,
          "stairs": false
        },
        {
          "from": "c_right_wing",
          "to": "room_right_1",
          "weight": 4,
          "stairs": false
        },
        {
          "from": "c_right_wing",
          "to": "room_large_r",
          "weight": 17,
          "stairs": false
        },
        {
          "from": "c_north",
          "to": "room_nw_1",
          "weight": 42,
          "stairs": false
        },
        {
          "from": "c_north",
          "to": "room_ne_1",
          "weight": 42,
          "stairs": false
        },
        {
          "from": "room_nw_1",
          "to": "room_nw_top",
          "weight": 18,
          "stairs": false
        },
        {
          "from": "room_nw_1",
          "to": "room_nw_mid",
          "weight": 15,
          "stairs": false
        },
        {
          "from": "room_ne_1",
          "to": "room_ne_top",
          "weight": 18,
          "stairs": false
        },
        {
          "from": "room_ne_1",
          "to": "room_ne_mid",
          "weight": 15,
          "stairs": false
        }
      ],
      "pois": [
        {
          "nodeId": "entrance",
          "icon": "ЁЯЪк",
          "category": "entrance",
          "description": {
            "en": "Main entrance of the police station",
            "ar": "╪з┘Д┘Е╪п╪о┘Д ╪з┘Д╪▒╪ж┘К╪│┘К ┘Д┘Е╪▒┘Г╪▓ ╪з┘Д╪┤╪▒╪╖╪й",
            "hi": "рдкреБрд▓рд┐рд╕ рд╕реНрдЯреЗрд╢рди рдХрд╛ рдореБрдЦреНрдп рдкреНрд░рд╡реЗрд╢ рджреНрд╡рд╛рд░"
          }
        },
        {
          "nodeId": "reception",
          "icon": "ЁЯПв",
          "category": "service",
          "description": {
            "en": "Reception counter тАФ check in here",
            "ar": "┘Е┘Г╪к╪и ╪з┘Д╪з╪│╪к┘В╪и╪з┘Д тАФ ╪│╪м┘Д ┘З┘Ж╪з",
            "hi": "рд░рд┐рд╕реЗрдкреНрд╢рди рдХрд╛рдЙрдВрдЯрд░ тАФ рдпрд╣рд╛рдБ рдЪреЗрдХ рдЗрди рдХрд░реЗрдВ"
          }
        },
        {
          "nodeId": "information",
          "icon": "тД╣я╕П",
          "category": "service",
          "description": {
            "en": "Information desk тАФ general inquiries",
            "ar": "┘Е┘Г╪к╪и ╪з┘Д╪з╪│╪к╪╣┘Д╪з┘Е╪з╪к тАФ ╪з┘Д╪з╪│╪к┘Б╪│╪з╪▒╪з╪к ╪з┘Д╪╣╪з┘Е╪й",
            "hi": "рд╕реВрдЪрдирд╛ рдбреЗрд╕реНрдХ тАФ рд╕рд╛рдорд╛рдиреНрдп рдкреВрдЫрддрд╛рдЫ"
          }
        },
        {
          "nodeId": "male_toilets",
          "icon": "ЁЯЪ╣",
          "category": "facility",
          "description": {
            "en": "Male toilets тЩ┐",
            "ar": "╪п┘И╪▒╪з╪к ┘Е┘К╪з┘З ╪з┘Д╪▒╪м╪з┘Д тЩ┐",
            "hi": "рдкреБрд░реБрд╖ рд╢реМрдЪрд╛рд▓рдп тЩ┐"
          }
        },
        {
          "nodeId": "female_toilet",
          "icon": "ЁЯЪ║",
          "category": "facility",
          "description": {
            "en": "Female toilet тЩ┐",
            "ar": "╪п┘И╪▒╪з╪к ┘Е┘К╪з┘З ╪з┘Д┘Ж╪│╪з╪б тЩ┐",
            "hi": "рдорд╣рд┐рд▓рд╛ рд╢реМрдЪрд╛рд▓рдп тЩ┐"
          }
        },
        {
          "nodeId": "room_nw_1",
          "icon": "ЁЯЪЧ",
          "category": "department",
          "description": {
            "en": "Traffic fines, licenses & vehicle services",
            "ar": "┘Е╪о╪з┘Д┘Б╪з╪к ╪з┘Д┘Е╪▒┘И╪▒ ┘И╪з┘Д╪▒╪о╪╡ ┘И╪о╪п┘Е╪з╪к ╪з┘Д┘Е╪▒┘Г╪и╪з╪к",
            "hi": "рдЯреНрд░реИрдлрд╝рд┐рдХ рдЬреБрд░реНрдорд╛рдирд╛, рд▓рд╛рдЗрд╕реЗрдВрд╕ рдФрд░ рд╡рд╛рд╣рди рд╕реЗрд╡рд╛рдПрдВ"
          }
        },
        {
          "nodeId": "room_ne_1",
          "icon": "ЁЯФН",
          "category": "department",
          "description": {
            "en": "File reports & criminal case inquiries",
            "ar": "╪к┘В╪п┘К┘Е ╪з┘Д╪и┘Д╪з╪║╪з╪к ┘И╪з┘Д╪з╪│╪к╪╣┘Д╪з┘Е ╪╣┘Ж ╪з┘Д┘В╪╢╪з┘К╪з ╪з┘Д╪м┘Ж╪з╪ж┘К╪й",
            "hi": "рд░рд┐рдкреЛрд░реНрдЯ рджрд░реНрдЬ рдХрд░реЗрдВ рдФрд░ рдЖрдкрд░рд╛рдзрд┐рдХ рдорд╛рдорд▓реЛрдВ рдХреА рдЬрд╛рдВрдЪ"
          }
        },
        {
          "nodeId": "room_large_l",
          "icon": "ЁЯдЭ",
          "category": "facility",
          "description": {
            "en": "Conference room for meetings",
            "ar": "┘В╪з╪╣╪й ╪з╪м╪к┘Е╪з╪╣╪з╪к",
            "hi": "рдмреИрдардХ рдХреЗ рд▓рд┐рдП рд╕рдореНрдореЗрд▓рди рдХрдХреНрд╖"
          }
        },
        {
          "nodeId": "room_large_r",
          "icon": "ЁЯУЛ",
          "category": "department",
          "description": {
            "en": "Investigation & inquiry room",
            "ar": "╪║╪▒┘Б╪й ╪з┘Д╪к╪н┘В┘К┘В ┘И╪з┘Д╪з╪│╪к┘Б╪│╪з╪▒",
            "hi": "рдЬрд╛рдВрдЪ рдФрд░ рдкреВрдЫрддрд╛рдЫ рдХрдХреНрд╖"
          }
        },
        {
          "nodeId": "room_nw_top",
          "icon": "тнР",
          "category": "department",
          "description": {
            "en": "Station commander's office",
            "ar": "┘Е┘Г╪к╪и ┘В╪з╪ж╪п ╪з┘Д┘Е╪▒┘Г╪▓",
            "hi": "рд╕реНрдЯреЗрд╢рди рдХрдорд╛рдВрдбрд░ рдХрд╛ рдХрд╛рд░реНрдпрд╛рд▓рдп"
          }
        },
        {
          "nodeId": "room_nw_mid",
          "icon": "ЁЯдЭ",
          "category": "department",
          "description": {
            "en": "Community services & public relations",
            "ar": "╪о╪п┘Е╪з╪к ┘Е╪м╪к┘Е╪╣┘К╪й ┘И╪╣┘Д╪з┘В╪з╪к ╪╣╪з┘Е╪й",
            "hi": "рд╕рд╛рдореБрджрд╛рдпрд┐рдХ рд╕реЗрд╡рд╛рдПрдВ рдФрд░ рдЬрдирд╕рдВрдкрд░реНрдХ"
          }
        },
        {
          "nodeId": "parking",
          "icon": "ЁЯЕ┐я╕П",
          "category": "facility",
          "description": {
            "en": "Parking area",
            "ar": "┘Е┘Ж╪╖┘В╪й ╪з┘Д┘Е┘И╪з┘В┘Б",
            "hi": "рдкрд╛рд░реНрдХрд┐рдВрдЧ рдХреНрд╖реЗрддреНрд░"
          }
        }
      ]
    }
  ]
}